ledcontroller/__init__.py
ledcontroller-1.3.0.dist-info/DESCRIPTION.rst
ledcontroller-1.3.0.dist-info/METADATA
ledcontroller-1.3.0.dist-info/RECORD
ledcontroller-1.3.0.dist-info/WHEEL
ledcontroller-1.3.0.dist-info/metadata.json
ledcontroller-1.3.0.dist-info/top_level.txt
