Metadata-Version: 2.0
Name: ledcontroller
Version: 1.3.0
Summary: Controller library for limitlessled/easybulb/milight Wi-Fi LEDs
Home-page: https://github.com/ojarva/python-ledcontroller
Author: Olli Jarva
Author-email: olli@jarva.fi
License: BSD
Keywords: applight applamp dekolight easybulb ilight limitlessled led ledme milight wifi
Platform: UNKNOWN
Classifier: Development Status :: 5 - Production/Stable
Classifier: Topic :: Home Automation
Classifier: Intended Audience :: Developers
Classifier: License :: OSI Approved :: BSD License
Classifier: Programming Language :: Python :: 2.7
Classifier: Programming Language :: Python :: 3
Classifier: Programming Language :: Python :: 3.2
Classifier: Programming Language :: Python :: 3.3
Classifier: Programming Language :: Python :: 3.4
Classifier: Programming Language :: Python :: 3.5
Classifier: Programming Language :: Python :: Implementation :: PyPy
Provides-Extra: dev
Requires-Dist: twine; extra == 'dev'
Requires-Dist: wheel; extra == 'dev'
